zhihu/__init__.py
zhihu/zhihu.py
zhihu_cli-1.2.0.dist-info/LICENSE
zhihu_cli-1.2.0.dist-info/METADATA
zhihu_cli-1.2.0.dist-info/WHEEL
zhihu_cli-1.2.0.dist-info/top_level.txt
zhihu_cli-1.2.0.dist-info/RECORD
