Metadata-Version: 2.1
Name: zhihu-cli
Version: 1.2.0
Summary: zhihu
Home-page: https://github.com/deplives/zhihu
Author: zhangbo
Author-email: deplives.zhang@gmail.com
License: MIT
Platform: UNKNOWN
Classifier: Programming Language :: Python :: 3.6
Classifier: License :: OSI Approved :: MIT License
Classifier: Operating System :: OS Independent
Requires-Dist: requests (==2.21.0)
Requires-Dist: beautifulsoup4 (==4.7.1)
Requires-Dist: lxml (==4.3.4)
